bw2agg/__init__.py
bw2agg/aggregate.py
bw2agg/scores.py
bw2agg/utils.py
bw2agg-0.1.2.dist-info/LICENSE.txt
bw2agg-0.1.2.dist-info/METADATA
bw2agg-0.1.2.dist-info/WHEEL
bw2agg-0.1.2.dist-info/top_level.txt
bw2agg-0.1.2.dist-info/RECORD
