Metadata-Version: 2.1
Name: bw2agg
Version: 0.1.2
Summary: Extension to brightway2 package to create and work with aggregated data
Home-page: https://github.com/pascallesage/brightway2-aggregated
Author: Pascal Lesage
Author-email: pascal.lesage@polymtl.ca
License: UNKNOWN
Platform: UNKNOWN
Classifier: Programming Language :: Python :: 3.7
Classifier: License :: OSI Approved :: MIT License
Classifier: Operating System :: OS Independent
Classifier: Intended Audience :: End Users/Desktop
Classifier: Intended Audience :: Developers
Classifier: Intended Audience :: Science/Research
Classifier: Operating System :: MacOS :: MacOS X
Classifier: Operating System :: Microsoft :: Windows
Classifier: Operating System :: POSIX
Classifier: Topic :: Scientific/Engineering :: Information Analysis
Classifier: Topic :: Scientific/Engineering :: Mathematics
Requires-Dist: bw2calc
Requires-Dist: bw2data
Requires-Dist: numpy
